pocketsmith_web/__init__.py
pocketsmith_web/pusher.py
pocketsmith_web/types.py
pocketsmith_web/util/__init__.py
pocketsmith_web/util/event_stream.py
pocketsmith_web/web.py
pocketsmith_web_client-0.1.1.dist-info/LICENSE
pocketsmith_web_client-0.1.1.dist-info/WHEEL
pocketsmith_web_client-0.1.1.dist-info/METADATA
pocketsmith_web_client-0.1.1.dist-info/RECORD
