Metadata-Version: 2.1
Name: pocketsmith-web-client
Version: 0.1.1
Summary: Pocketsmith web/realtime client, for things the API does not provide
Home-page: https://github.com/theY4Kman/python-pocketsmith-api
License: MIT
Author: Zach "theY4Kman" Kanzler
Author-email: they4kman@gmail.com
Requires-Python: >=3.6.1
Classifier: Development Status :: 4 - Beta
Classifier: Intended Audience :: Developers
Classifier: Intended Audience :: Financial and Insurance Industry
Classifier: License :: OSI Approved :: MIT License
Classifier: Programming Language :: Python :: 3
Classifier: Programming Language :: Python :: 3.7
Classifier: Programming Language :: Python :: 3.8
Classifier: Programming Language :: Python :: 3.9
Classifier: Topic :: Internet :: WWW/HTTP
Requires-Dist: aiostream (>=0.4.1,<0.5.0)
Requires-Dist: beautifulsoup4 (>=4.7.1,<5.0.0)
Requires-Dist: httpx (>=0.15.5,<0.16.0)
Requires-Dist: lifter (>=0.4.1,<0.5.0)
Requires-Dist: pyotp (>=2.3.0,<3.0.0)
Requires-Dist: websockets (>=8.1,<9.0)
